pysure/__init__.py
pysure/pysure.py
pysure-0.1.1.dist-info/LICENSE
pysure-0.1.1.dist-info/METADATA
pysure-0.1.1.dist-info/WHEEL
pysure-0.1.1.dist-info/top_level.txt
pysure-0.1.1.dist-info/RECORD
