Metadata-Version: 2.1
Name: pysure
Version: 0.1.1
Summary: Surrogate residuals for logistic regression
Home-page: https://github.com/jmccrosky/pysure
Author: Jesse McCrosky
Author-email: mccrosky@gmail.com
License: MIT
Platform: UNKNOWN
License-File: LICENSE
